recomenda/__init__.py
recomenda/core/__init__.py
recomenda/core/config.py
recomenda/core/logger.py
recomenda/services/__init__.py
recomenda/services/async_recommender.py
recomenda/services/base_recommender.py
recomenda/services/embedder.py
recomenda/services/recommender.py
recomenda/utils/__init__.py
recomenda/utils/hashing.py
recomenda-0.1.5.dist-info/METADATA
recomenda-0.1.5.dist-info/WHEEL
recomenda-0.1.5.dist-info/RECORD
