Metadata-Version: 2.1
Name: recomenda
Version: 0.1.5
Summary: A recommendation system package using OpenAI embeddings
Home-page: https://github.com/kevinqz/recomenda
License: MIT
Keywords: recommendation,openai,embeddings
Author: Kevin Saltarelli
Author-email: kevinqz@gmail.com
Requires-Python: >=3.10.0,<3.12
Classifier: License :: OSI Approved :: MIT License
Classifier: Operating System :: OS Independent
Classifier: Programming Language :: Python :: 3
Classifier: Programming Language :: Python :: 3.10
Classifier: Programming Language :: Python :: 3.11
Requires-Dist: openai (>=1.47.1,<2.0.0)
Requires-Dist: psycopg2-binary (>=2.9.9,<3.0.0)
Requires-Dist: pydantic-settings (>=2.5.2,<3.0.0)
Requires-Dist: pytz (>=2024.2,<2025.0)
Requires-Dist: scipy (>=1.14.1,<2.0.0)
Requires-Dist: sqlmodel (>=0.0.22,<0.0.23)
Project-URL: Repository, https://github.com/kevinqz/recomenda
